README
berry.py
setup.py
berry.egg-info/PKG-INFO
berry.egg-info/SOURCES.txt
berry.egg-info/dependency_links.txt
berry.egg-info/top_level.txt