Metadata-Version: 1.0
Name: berry
Version: 0.3.1
Summary: a minimal DSL for building a WSGI app
Home-page: http://soundofemptiness.com/projects/berry
Author: Adeel Ahmad Khan
Author-email: adeel2@umbc.edu
License: UNKNOWN
Platform: UNKNOWN
Classifier: Development Status :: 5 - Production/Stable
Classifier: License :: OSI Approved :: MIT License
